mailtarget_sdk/__init__.py
mailtarget_sdk/layang.py
mailtarget_sdk/message.py
mailtarget_sdk/message_component.py
mailtarget_sdk/validation.py
tests/__init__.py
tests/test_layang.py
mailtarget_sdk-0.1.0.dist-info/METADATA
mailtarget_sdk-0.1.0.dist-info/WHEEL
mailtarget_sdk-0.1.0.dist-info/top_level.txt
mailtarget_sdk-0.1.0.dist-info/RECORD
