Metadata-Version: 2.1
Name: mailtarget_sdk
Version: 0.1.0
Summary: SDK Python untuk Mailtarget API
Home-page: https://gitlab.com/mailtarget/integrations/mailtarget-python-sdk
Author: Wisnu Eka Saputra
Author-email: wisnu.eka@mtarget.co
Classifier: Programming Language :: Python :: 3
Classifier: License :: OSI Approved :: MIT License
Classifier: Operating System :: OS Independent
Requires-Python: >=3.6
Requires-Dist: requests
Requires-Dist: pytest
